{
	"Drawback": ["不利", "ふり", "img/bonsai.gif", "sound/fire.mp3"],
    "Evening": ["夕刻", "ゆうこく", "img/bonsai.gif", "sound/water.mp3"],
	"Shoal": ["遠浅", "とおあさ", "img/bonsai.gif", "sound/tree.mp3"],
	"Midnight": ["深夜", "しんや", "img/bonsai.gif", "sound/gold.mp3"],
	"Poverty": ["貧困", "ひんこん", "img/bonsai.gif", "sound/earth.mp3"],
	"Permission": ["許可", "きょか", "img/bonsai.gif", "sound/present.mp3"],
	"WorldHistory": ["世界史", "せかいし", "img/bonsai.gif", "sound/minute.mp3"],
	"Incidence": ["入射", "にゅうしゃ", "img/bonsai.gif", "sound/year.mp3"],
	"Convene": ["招集", "しょうしゅう", "img/bonsai.gif", "sound/big.mp3"],
	"Transportation": ["運送", "うんそう", "img/bonsai.gif", "sound/center.mp3"],
	"WaitingRoom": ["待合室", "まちあいしつ", "img/bonsai.gif", "sound/small.mp3"],
	"ColdStorage": ["冷蔵", "れいぞう", "img/bonsai.gif", "sound/few.mp3"],
	"Warehouse": ["倉庫", "そうこ", "img/bonsai.gif", "sound/many.mp3"],
	"BulletTrain": ["新幹線", "しんかんせん", "img/bonsai.gif", "sound/above.mp3"],
	"HighRise": ["高層", "こうそう", "img/bonsai.gif", "sound/below.mp3"],
	"Hokuriku": ["北陸", "ほくりく", "img/bonsai.gif", "sound/right.mp3"],
	"Maintenance": ["整備", "せいび", "img/bonsai.gif", "sound/le
	ft.mp3"],
	"Upbringing": ["来歴", "らいれき", "img/bonsai.gif", "sound/stone.mp3"],
	"Postponement": ["延期", "えんき", "img/bonsai.gif", "sound/person.mp3"],
	"Constitution": ["構成", "こうせい", "img/bonsai.gif", "sound/person.mp3"],
	"Warmth": ["温暖", "おんだん", "img/bonsai.gif", "sound/person.mp3"],
	"Degree": ["程度", "ていど", "img/bonsai.gif", "sound/person.mp3"],
	"Prefectures": ["都道府県", "とどうふけん", "img/bonsai.gif", "sound/enter.mp3"],
	"Product": ["製品",  "せいひん", "img/bonsai.gif", "sound/appear.mp3"],
	"Satellite": ["衛星",  "えいせい", "img/bonsai.gif", "sound/appear.mp3"],
	"Protection": ["保護",  "ほご", "img/bonsai.gif", "sound/mouth.mp3"],
	"AfterSchool": ["放課後",  "ほうかご", "img/bonsai.gif", "sound/outside.mp3"],
	"Theories": ["諸説",  "しょせつ", "img/bonsai.gif", "sound/eye.mp3"],
	"Favorable": ["好調",  "こうちょう", "img/bonsai.gif", "sound/hand.mp3"],
	"Smuggling": ["密輸",  "みつゆ", "img/bonsai.gif", "sound/leg.mp3"],
	"Handbook": ["要覧",  "ようらん", "img/bonsai.gif", "sound/stop.mp3"],
	"Policy": ["方針",  "ほうしん", "img/bonsai.gif", "sound/stop.mp3"],
	"Difficulty": ["難易度",  "なんいど", "img/bonsai.gif", "sound/stop.mp3"]
}